mathextra/__init__.py
mathextra/area.py
mathextra/arithmetic_ops.py
mathextra/conversions.py
mathextra/factor.py
mathextra/formulas.py
mathextra-1.3.dist-info/METADATA
mathextra-1.3.dist-info/WHEEL
mathextra-1.3.dist-info/top_level.txt
mathextra-1.3.dist-info/RECORD
