Metadata-Version: 2.1
Name: mathextra
Version: 1.3
Summary: Extra math functions
Home-page: UNKNOWN
Author: TheCoder1001 (Atharv Baluja)
Author-email: <thecoder1001yt@gmail.com>
License: UNKNOWN
Keywords: python,math,useful math functions
Platform: UNKNOWN
Classifier: Development Status :: 5 - Production/Stable
Classifier: Intended Audience :: Developers
Classifier: Programming Language :: Python :: 3
Classifier: Operating System :: Unix
Classifier: Operating System :: MacOS
Classifier: Operating System :: Microsoft :: Windows
